geneci/main.py
geneci/utils.py
geneci-4.0.1.2.dist-info/entry_points.txt
geneci-4.0.1.2.dist-info/LICENSE
geneci-4.0.1.2.dist-info/WHEEL
geneci-4.0.1.2.dist-info/METADATA
geneci-4.0.1.2.dist-info/RECORD
