Metadata-Version: 2.1
Name: geneci
Version: 4.0.1.2
Summary: Software package whose main functionality consists of an evolutionary algorithm to determine the optimal ensemble of machine learning techniques for genetic network inference based on the confidence levels and topological characteristics of its results.
License: MIT
Author: adrian_segura
Author-email: adrianseor.99@uma.es
Requires-Python: >=3.10.7,<3.11
Classifier: License :: OSI Approved :: MIT License
Classifier: Programming Language :: Python :: 3
Requires-Dist: click (<8.1.7)
Requires-Dist: docker (>=7.1.0,<8.0.0)
Requires-Dist: iteround (>=1.0.4,<2.0.0)
Requires-Dist: matplotlib (>=3.10.0,<4.0.0)
Requires-Dist: pandas (>=2.2.3,<3.0.0)
Requires-Dist: plotly (>=6.0.0,<7.0.0)
Requires-Dist: scikit-learn (>=1.6.1,<2.0.0)
Requires-Dist: scipy (>=1.15.2,<2.0.0)
Requires-Dist: tornado (>=6.4.2,<7.0.0)
Requires-Dist: tqdm (>=4.67.1,<5.0.0)
Requires-Dist: typer[all] (>=0.6,<0.7)
